src/__init__.py
this_is_a_test_package11-0.0.1.dist-info/LICENSE
this_is_a_test_package11-0.0.1.dist-info/METADATA
this_is_a_test_package11-0.0.1.dist-info/WHEEL
this_is_a_test_package11-0.0.1.dist-info/top_level.txt
this_is_a_test_package11-0.0.1.dist-info/RECORD
