Metadata-Version: 2.1
Name: this-is-a-test-package11
Version: 0.0.1
Summary: Test package - do not download
Home-page: https://github.com/example
Download-URL: https://github.com/example
Author: dsa
Author-email: test <test@test.com>
License: Apache 2.0
Project-URL: Homepage, https://github.com/example
Project-URL: Bug Tracker, https://github.com/example
Classifier: Programming Language :: Python :: 3
Classifier: License :: OSI Approved :: MIT License
Classifier: Operating System :: OS Independent
Requires-Python: >=3.9
License-File: LICENSE
